{"title":"training_data","createdDate":"2025-05-03T02:11:37Z","dataPathRelativeToProjectURL":"..\/training_data\/","dataURL":"file:\/\/\/Users\/sshlyk\/Dev\/pomidor\/training\/training_data\/","pathType":0,"modifiedDate":"2025-05-03T02:17:55Z","version":"1.0","preferredFilename":"training_data","experimentIDs":["5178C514-F6DF-449E-93D5-AD8831193FA7"],"dataResult":{"dataSourceID":"9902EB83-1CB4-455C-9AFA-49100F3CC281","dataURL":"file:\/\/\/Users\/sshlyk\/Dev\/pomidor\/training\/training_data\/","createdDate":"2025-05-03T02:11:37Z"},"id":"9902EB83-1CB4-455C-9AFA-49100F3CC281","activityEntities":["dataSourceCreated",[{"id":"EECC4E3A-8E77-4909-BCF0-4AAF6D670669","title":"Data Source Created","event":"dataSourceCreated","subtitle":"training_data","createdDate":"2025-05-03T02:11:37Z"}],"dataSourceTrainingStarted",[{"id":"21AF0BB6-3696-45F2-BAF9-03292482ACBD","title":"Used By","event":"dataSourceTrainingStarted","subtitle":"MovieTitlesDetection 1","createdDate":"2025-05-03T02:17:55Z"}],"dataSourceMetrics",[{"id":"42004B5F-41F0-4E8D-A67B-FF547BF00A3C","title":"Data Summary","event":"dataSourceMetrics","subtitle":"1 Classes, 40 Items","createdDate":"2025-05-03T02:17:55Z"}]]}